azure/mgmt/mongocluster/__init__.py
azure/mgmt/mongocluster/_client.py
azure/mgmt/mongocluster/_configuration.py
azure/mgmt/mongocluster/_patch.py
azure/mgmt/mongocluster/_validation.py
azure/mgmt/mongocluster/_version.py
azure/mgmt/mongocluster/py.typed
azure/mgmt/mongocluster/_utils/__init__.py
azure/mgmt/mongocluster/_utils/model_base.py
azure/mgmt/mongocluster/_utils/serialization.py
azure/mgmt/mongocluster/aio/__init__.py
azure/mgmt/mongocluster/aio/_client.py
azure/mgmt/mongocluster/aio/_configuration.py
azure/mgmt/mongocluster/aio/_patch.py
azure/mgmt/mongocluster/aio/operations/__init__.py
azure/mgmt/mongocluster/aio/operations/_operations.py
azure/mgmt/mongocluster/aio/operations/_patch.py
azure/mgmt/mongocluster/models/__init__.py
azure/mgmt/mongocluster/models/_enums.py
azure/mgmt/mongocluster/models/_models.py
azure/mgmt/mongocluster/models/_patch.py
azure/mgmt/mongocluster/operations/__init__.py
azure/mgmt/mongocluster/operations/_operations.py
azure/mgmt/mongocluster/operations/_patch.py
azure_mgmt_mongocluster-1.1.0.dist-info/licenses/LICENSE
azure_mgmt_mongocluster-1.1.0.dist-info/METADATA
azure_mgmt_mongocluster-1.1.0.dist-info/WHEEL
azure_mgmt_mongocluster-1.1.0.dist-info/top_level.txt
azure_mgmt_mongocluster-1.1.0.dist-info/RECORD
